py_overlay_evm/__init__.py
py_overlay_evm/evm.py
py_overlay_evm/keccak.py
py_overlay_evm/rpc.py
py_overlay_evm/solidity.py
py_overlay_evm-0.1.0.dist-info/LICENSE
py_overlay_evm-0.1.0.dist-info/METADATA
py_overlay_evm-0.1.0.dist-info/WHEEL
py_overlay_evm-0.1.0.dist-info/top_level.txt
py_overlay_evm-0.1.0.dist-info/RECORD
