Metadata-Version: 2.1
Name: py-overlay-evm
Version: 0.1.0
Summary: Ethereum VM aimed at a mock execution of smart contracts
Author-email: Andrei Dubovik <andrei@dubovik.eu>
Project-URL: Homepage, https://github.com/andrei-dubovik/py-overlay-evm
Project-URL: Repository, https://github.com/andrei-dubovik/py-overlay-evm.git
Keywords: evm,ethereum virtual machine,smart contract,simulation
Classifier: License :: OSI Approved :: GNU General Public License v3 (GPLv3)
License-File: LICENSE
Requires-Dist: numpy
Requires-Dist: requests
